<annotation>
  <folder>Cable-Color23022002/cable</folder>
  <filename>Cable-Color23022002/cable_color_red_230220_1248.jpg</filename>
  <source>
    <database>Unknown</database>
    <annotation>Unknown</annotation>
    <image>Unknown</image>
  </source>
  <size>
    <width>1280</width>
    <height>960</height>
    <depth></depth>
  </size>
  <segmented>0</segmented>
  <object>
    <name>red</name>
    <truncated>0</truncated>
    <occluded>0</occluded>
    <difficult>0</difficult>
    <bndbox>
      <xmin>77.62</xmin>
      <ymin>241.28</ymin>
      <xmax>599.74</xmax>
      <ymax>760.85</ymax>
    </bndbox>
    <attributes>
      <attribute>
        <name>rotation</name>
        <value>0.0</value>
      </attribute>
    </attributes>
  </object>
</annotation>
